mercedestrenz/__init__.py
mercedestrenz/data.py
mercedestrenz/datasets/__init__.py
mercedestrenz/datasets/mercedes.csv
mercedestrenz/models/__init__.py
mercedestrenz/models/mercedes_price_prediction_v1.joblib
mercedestrenz/predict.py
mercedestrenz/train.py
mercedestrenz/visualizations.py
mercedestrenz-1.0.0.dist-info/METADATA
mercedestrenz-1.0.0.dist-info/WHEEL
mercedestrenz-1.0.0.dist-info/LICENSE
mercedestrenz-1.0.0.dist-info/RECORD
