Metadata-Version: 2.1
Name: mercedestrenz
Version: 1.0.0
Summary: A package to inspect and analyze used Mercedes Benz car prices.
License: MIT
Author: Ty Andrews
Requires-Python: >=3.9,<4.0
Classifier: License :: OSI Approved :: MIT License
Classifier: Programming Language :: Python :: 3
Classifier: Programming Language :: Python :: 3.9
Classifier: Programming Language :: Python :: 3.10
Classifier: Programming Language :: Python :: 3.11
Requires-Dist: altair (>=4.2.0,<5.0.0)
Requires-Dist: numpy (>=1.24.1,<2.0.0)
Requires-Dist: pandas (>=1.5.3,<2.0.0)
Requires-Dist: scikit-learn (==1.2.1)
